prithvi_client.py
prithvi_py_sdk-0.1.0.dist-info/METADATA
prithvi_py_sdk-0.1.0.dist-info/WHEEL
prithvi_py_sdk-0.1.0.dist-info/top_level.txt
prithvi_py_sdk-0.1.0.dist-info/RECORD
