Metadata-Version: 2.4
Name: prithvi-py-sdk
Version: 0.1.0
Summary: Official Python SDK for Prithvi in-memory key-value database.
Home-page: https://github.com/psidh/prithvi-py-sdk
Author: Sidharth P
Author-email: philkhanasidharth14@gmail.com
Classifier: Programming Language :: Python :: 3
Classifier: License :: OSI Approved :: MIT License
Classifier: Operating System :: OS Independent
Requires-Python: >=3.7
Dynamic: author
Dynamic: author-email
Dynamic: classifier
Dynamic: description
Dynamic: description-content-type
Dynamic: home-page
Dynamic: requires-python
Dynamic: summary
